odoo/addons/account_invoice_overdue_warn_public/README.rst
odoo/addons/account_invoice_overdue_warn_public/__init__.py
odoo/addons/account_invoice_overdue_warn_public/__manifest__.py
odoo/addons/account_invoice_overdue_warn_public/i18n/es.po
odoo/addons/account_invoice_overdue_warn_public/static/description/icon.png
odoo/addons/account_invoice_overdue_warn_public/views/res_partner_views.xml
odoo_addon_account_invoice_overdue_warn_public-17.0.1.0.0.dist-info/METADATA
odoo_addon_account_invoice_overdue_warn_public-17.0.1.0.0.dist-info/WHEEL
odoo_addon_account_invoice_overdue_warn_public-17.0.1.0.0.dist-info/top_level.txt
odoo_addon_account_invoice_overdue_warn_public-17.0.1.0.0.dist-info/RECORD
